llama_server_client/__init__.py
llama_server_client/async_client.py
llama_server_client/base_client.py
llama_server_client/client.py
llama_server_client/error.py
llama_server_client/schema/__init__.py
llama_server_client/schema/base.py
llama_server_client/schema/completion.py
llama_server_client/schema/document.py
llama_server_client/schema/health_check.py
llama_server_client/schema/session_state.py
llama_server_client/schema/split.py
llama_server_client/schema/summary.py
llama_server_client/schema/zmq_message_header.py
llama_server_client/schema/zmq_response.py
llama_server_client/tests/__init__.py
llama_server_client/tests/async_client_load_tests.py
llama_server_client/tests/async_client_stream_load_tests.py
llama_server_client/tests/async_client_tests.py
llama_server_client/tests/client_parallel_load_test.py
llama_server_client/tests/client_tests.py
llama_server_client/tests/msgpack_tests.py
llama_server_client/tests/zmq_message_test.py
llama_server_client-1.2.2.dist-info/METADATA
llama_server_client-1.2.2.dist-info/WHEEL
llama_server_client-1.2.2.dist-info/top_level.txt
llama_server_client-1.2.2.dist-info/RECORD
